wolof_translate/__init__.py
wolof_translate/data/__init__.py
wolof_translate/data/dataset_v1.py
wolof_translate/data/dataset_v2.py
wolof_translate/data/dataset_v3.py
wolof_translate/data/dataset_v3_2.py
wolof_translate/data/dataset_v4.py
wolof_translate/data/dataset_v5.py
wolof_translate/models/__init__.py
wolof_translate/models/transformers/__init__.py
wolof_translate/models/transformers/main.py
wolof_translate/models/transformers/main_2.py
wolof_translate/models/transformers/optimization.py
wolof_translate/models/transformers/position.py
wolof_translate/models/transformers/size.py
wolof_translate/pipe/__init__.py
wolof_translate/pipe/nlp_pipeline.py
wolof_translate/tokenizers/__init__.py
wolof_translate/trainers/__init__.py
wolof_translate/trainers/transformer_trainer.py
wolof_translate/trainers/transformer_trainer_custom.py
wolof_translate/trainers/transformer_trainer_ml.py
wolof_translate/trainers/transformer_trainer_ml_.py
wolof_translate/utils/__init__.py
wolof_translate/utils/bucket_iterator.py
wolof_translate/utils/database_manager.py
wolof_translate/utils/display_predictions.py
wolof_translate/utils/download_model.py
wolof_translate/utils/evaluate_custom.py
wolof_translate/utils/evaluation.py
wolof_translate/utils/extract_new_sentences.py
wolof_translate/utils/extract_poems.py
wolof_translate/utils/extract_sentences.py
wolof_translate/utils/recuperate_datasets.py
wolof_translate/utils/recuperate_datasets_trunc.py
wolof_translate/utils/send_model.py
wolof_translate/utils/sent_corrections.py
wolof_translate/utils/sent_transformers.py
wolof_translate/utils/sent_unification.py
wolof_translate/utils/split_with_valid.py
wolof_translate/utils/tokenize_text.py
wolof_translate/utils/training.py
wolof_translate/utils/trunc_hg_training.py
wolof_translate/utils/improvements/__init__.py
wolof_translate/utils/improvements/end_marks.py
wolof_translate-0.0.4.dist-info/METADATA
wolof_translate-0.0.4.dist-info/WHEEL
wolof_translate-0.0.4.dist-info/top_level.txt
wolof_translate-0.0.4.dist-info/RECORD
